timedelta_nice_format/__init__.py
timedelta_nice_format/main.py
timedelta_nice_format-0.1.0.dist-info/LICENSE.txt
timedelta_nice_format-0.1.0.dist-info/WHEEL
timedelta_nice_format-0.1.0.dist-info/METADATA
timedelta_nice_format-0.1.0.dist-info/RECORD
