Metadata-Version: 2.1
Name: timedelta-nice-format
Version: 0.1.0
Summary: PYPI package with 2 functions to convert datetime.timedelta into string with nice format
License: MIT
Author: Stanislav Prokopyev
Author-email: stas.prokopiev@gmail.com
Requires-Python: >=3.7,<4.0
Classifier: License :: OSI Approved :: MIT License
Classifier: Programming Language :: Python :: 3
Classifier: Programming Language :: Python :: 3.10
Classifier: Programming Language :: Python :: 3.7
Classifier: Programming Language :: Python :: 3.8
Classifier: Programming Language :: Python :: 3.9
